nonebot_plugin_zyk_lightNVL/__init__.py
nonebot_plugin_zyk_lightNVL/config.py
nonebot_plugin_zyk_lightNVL/template.html
nonebot_plugin_zyk_lightNVL/work.py
nonebot_plugin_zyk_lightNVL-0.1.1.dist-info/LICENSE
nonebot_plugin_zyk_lightNVL-0.1.1.dist-info/METADATA
nonebot_plugin_zyk_lightNVL-0.1.1.dist-info/WHEEL
nonebot_plugin_zyk_lightNVL-0.1.1.dist-info/top_level.txt
nonebot_plugin_zyk_lightNVL-0.1.1.dist-info/RECORD
