Metadata-Version: 2.1
Name: nonebot-plugin-zyk-lightNVL
Version: 0.1.1
Summary: A plugin for nonebot2
Home-page: https://github.com/ZYKsslm/nonebot_plugin_zyk_lightNVL
Author: ZYKsslm
Author-email: 3119964735@qq.com
License: MIT LICENSE
License-File: LICENSE
Requires-Dist: httpx
Requires-Dist: colorama
Requires-Dist: lxml
Requires-Dist: fake-useragent
Requires-Dist: nonebot2
Requires-Dist: nonebot-plugin-htmlrender
Requires-Dist: nonebot-adapter-onebot
